{
  "BuildingSpec": {
    "SelectionSoundName": "Default",
    "LoopingSoundName": "",
    "BuildingCost": [
      {
        "Id": "Log",
        "Amount": 2
      },
      {
        "Id": "MetalBlock",
        "Amount": 3
      },
      {
        "Id": "TreatedPlank",
        "Amount": 4
      }
    ],
    "ScienceCost": 0,
    "PlaceFinished": false,
    "FinishableWithBeaversOnSite": true,
    "DrawRangeBoundsOnIt": false
  },
  "BlockObjectSpec": {
    "BlocksSpec": {
      "Size": {
        "X": 2,
        "Y": 2,
        "Z": 2
      },
      "BlockSpecs": [
        {
          "MatterBelow": "GroundOrStackable",
          "Occupations": "Floor, Bottom, Corners, Path",
          "Stackable": "None",
          "OccupyAllBelow": false,
          "Underground": false
        },
        {
          "MatterBelow": "GroundOrStackable",
          "Occupations": "Floor, Bottom, Corners, Path",
          "Stackable": "None",
          "OccupyAllBelow": false,
          "Underground": false
        },
        {
          "MatterBelow": "GroundOrStackable",
          "Occupations": "Floor, Bottom, Corners, Path",
          "Stackable": "None",
          "OccupyAllBelow": false,
          "Underground": false
        },
        {
          "MatterBelow": "GroundOrStackable",
          "Occupations": "-1",
          "Stackable": "None",
          "OccupyAllBelow": false,
          "Underground": false
        },
        {
          "MatterBelow": "Any",
          "Occupations": "None",
          "Stackable": "None",
          "OccupyAllBelow": false,
          "Underground": false
        },
        {
          "MatterBelow": "Any",
          "Occupations": "None",
          "Stackable": "None",
          "OccupyAllBelow": false,
          "Underground": false
        },
        {
          "MatterBelow": "Any",
          "Occupations": "None",
          "Stackable": "None",
          "OccupyAllBelow": false,
          "Underground": false
        },
        {
          "MatterBelow": "Any",
          "Occupations": "Floor, Bottom, Corners, Path",
          "Stackable": "None",
          "OccupyAllBelow": false,
          "Underground": false
        }
      ]
    },
    "Entrance": {
      "HasEntrance": true,
      "Coordinates": {
        "X": 1,
        "Y": -1,
        "Z": 0
      }
    },
    "BaseZ": 0,
    "Overridable": false,
    "Flippable": true
  },
  "BuildingAccessibleSpec": {
    "LocalAccess": {
      "X": 1.5,
      "Y": 0.1,
      "Z": 0.2
    },
    "ForceOneFinalAccess": false
  },
  "PlaceableBlockObjectSpec": {
    "ToolGroupId": "Wellbeing",
    "ToolOrder": 200,
    "ToolShape": "Square",
    "Layout": "Single",
    "CustomPivot": {
      "HasCustomPivot": false,
      "Coordinates": {
        "X": 0.0,
        "Y": 0.0,
        "Z": 0.0
      }
    },
    "CanBeAttachedToTerrainSide": false,
    "DevModeTool": false
  },
  "BuildingModelSpec": {
    "FinishedModelName": "#Finished",
    "UnfinishedModelName": "#Unfinished",
    "FinishedUncoveredModelName": "",
    "UndergroundModelName": "",
    "ConstructionModeModel": "Finished",
    "UndergroundModelDepth": 0
  },
  "FixedSlotManagerSpec": {},
  "TransformSlotInitializerSpec": {
    "Slots": [
      {
        "SlotKeyword": "Spot",
        "Animation": "ForcedIdle",
        "Inanimate": false,
        "RandomizeYRotation": false,
        "WaterSlot": false
      }
    ]
  },
  "EnterableSpec": {
    "OperatingState": "Finished",
    "LimitedCapacityFinished": true,
    "CapacityFinished": 3,
    "LimitedCapacityUnfinished": false,
    "CapacityUnfinished": 0
  },
  "AttractionSpec": {
    "Effects": [
      {
        "NeedId": "FrogStatue",
        "PointsPerHour": 1.5,
        "SatisfyToMaxValue": false
      }
    ]
  },
  "TemplateSpec": {
    "TemplateName": "FrogStatue.Folktails",
    "BackwardCompatibleTemplateNames": [],
    "RequiredFeatureToggle": "",
    "DisablingFeatureToggle": ""
  },
  "LabeledEntitySpec": {
    "DisplayNameLocKey": "Knatte.FrogStatue.DisplayName",
    "DescriptionLocKey": "Knatte.FrogStatue.Description",
    "FlavorDescriptionLocKey": "Knatte.FrogStatue.FlavorDescription",
    "Icon": "Knatte/Frogicons/Frogicon"
  },
  "EnterableLightingSpec": {},
  "FloodableFireSpec": {},
  "FireSpec": {
    "AttachmentId": "Fire.KAFrogfire"
  },
  "NightTimeLightControllerSpec": {},
  "TemplateAttachmentsSpec": {
    "Attachments": [
      {
        "AttachmentId": "Fire.KAFrogfire",
        "Prefab": "Buildings/Wellbeing/ContemplationSpot/ContemplationSpotFire",
        "Parent": "#Finished",
        "Position": {
          "X": 1.3,
          "Y": 0.23,
          "Z": 1.225
        },
        "Rotation": {
          "X": 0.0,
          "Y": 0.0,
          "Z": 0.0
        },
        "Scale": {
          "X": 2.0,
          "Y": 2.0,
          "Z": 2.0
        },
        "CreateInstantly": true
      }
    ]
  },
  "Children": {
    "#Finished": {
      "CollidersSpec": {
        "BoxColliders": [
          {
            "Center": {
              "X": 1.5,
              "Y": 0.5,
              "Z": 1.5
            },
            "Size": {
              "X": 0.8,
              "Y": 1.0,
              "Z": 0.8
            }
          },
          {
            "Center": {
              "X": 0.1,
              "Y": 0.15,
              "Z": 1.0
            },
            "Size": {
              "X": 0.2,
              "Y": 0.35,
              "Z": 2.0
            }
          },
          {
            "Center": {
              "X": 1.9,
              "Y": 0.15,
              "Z": 1.0
            },
            "Size": {
              "X": 0.2,
              "Y": 0.35,
              "Z": 2.0
            }
          },
          {
            "Center": {
              "X": 1.0,
              "Y": 0.15,
              "Z": 1.9
            },
            "Size": {
              "X": 2.0,
              "Y": 0.35,
              "Z": 0.2
            }
          },
          {
            "Center": {
              "X": 0.6,
              "Y": 0.15,
              "Z": 0.1
            },
            "Size": {
              "X": 1.2,
              "Y": 0.35,
              "Z": 0.2
            }
          },
          {
            "Center": {
              "X": 1.0,
              "Y": 0.015,
              "Z": 1.0
            },
            "Size": {
              "X": 2.0,
              "Y": 0.03,
              "Z": 2.0
            }
          }
        ],
        "SphereColliders": [],
        "CapsuleColliders": []
      },
      "Children": {
        "Model": {
          "TransformSpec": {
            "Position": {
              "X": 0.0,
              "Y": 0.0,
              "Z": 0.0
            },
            "Rotation": {
              "X": 0.0,
              "Y": 180.0,
              "Z": 0.0
            },
            "Scale": {
              "X": 1.0,
              "Y": 1.0,
              "Z": 1.0
            }
          },
          "TimbermeshSpec": {
            "Model": "Knatte/Buildings/Wellbeing/FrogStatue/FrogStatue.Model.Folktails"
          },
          "Children": {
            "#Slot#Spot1": {
              "TransformSpec": {
                "Position": {
                  "X": -0.72,
                  "Y": 0.067,
                  "Z": -1.521
                },
                "Rotation": {
                  "X": 0.0,
                  "Y": 270.0,
                  "Z": 0.0
                },
                "Scale": {
                  "X": 1.0,
                  "Y": 1.0,
                  "Z": 1.0
                }
              }
            },
            "#Slot#Spot2": {
              "TransformSpec": {
                "Position": {
                  "X": -0.912,
                  "Y": 0.06300001,
                  "Z": -0.809
                },
                "Rotation": {
                  "X": 359.4131,
                  "Y": 225.0,
                  "Z": 1.33409133E-08
                },
                "Scale": {
                  "X": 1.0,
                  "Y": 1.0,
                  "Z": 1.0
                }
              }
            },
            "#Slot#Spot3": {
              "TransformSpec": {
                "Position": {
                  "X": -1.528,
                  "Y": 0.06300001,
                  "Z": -0.653
                },
                "Rotation": {
                  "X": 359.4131,
                  "Y": 180.0,
                  "Z": 0.0
                },
                "Scale": {
                  "X": 1.0,
                  "Y": 1.0,
                  "Z": 1.0
                }
              }
            }
          }
        }
      }
    },
    "#Unfinished": {
      "Children": {
        "ConstructionBase2x2#nested": {
          "BlueprintPath": "ConstructionBases/ConstructionBase2x2/ConstructionBase2x2.blueprint"
        }
      }
    }
  }
}